hebcmkarel/__init__.py
hebcmkarel/app.py
hebcmkarel/karel.py
hebcmkarel/karelmain.py
hebcmkarel/settings.py
hebcmkarel/superkarel.py
hebcmkarel-0.3.data/data/Lib/site-packages/hebcmkarel/icons/edit.png
hebcmkarel-0.3.data/data/Lib/site-packages/hebcmkarel/icons/new.png
hebcmkarel-0.3.data/data/Lib/site-packages/hebcmkarel/icons/open.png
hebcmkarel-0.3.data/data/Lib/site-packages/hebcmkarel/icons/play.png
hebcmkarel-0.3.data/data/Lib/site-packages/hebcmkarel/icons/reload.png
hebcmkarel-0.3.data/data/Lib/site-packages/hebcmkarel/icons/reset.png
hebcmkarel-0.3.data/data/Lib/site-packages/hebcmkarel/icons/running.png
hebcmkarel-0.3.data/data/Lib/site-packages/hebcmkarel/icons/save.png
hebcmkarel-0.3.data/data/Lib/site-packages/hebcmkarel/icons/saveas.png
hebcmkarel-0.3.data/data/Lib/site-packages/hebcmkarel/icons/settings.png
hebcmkarel-0.3.data/data/Lib/site-packages/hebcmkarel/icons/stop.png
hebcmkarel-0.3.dist-info/METADATA
hebcmkarel-0.3.dist-info/WHEEL
hebcmkarel-0.3.dist-info/top_level.txt
hebcmkarel-0.3.dist-info/RECORD
