Metadata-Version: 2.1
Name: hebcmkarel
Version: 0.3
Summary: karel for python
Home-page: https://github.com/hbynlsl/karel
Author: hbynlsl
Author-email: hbynlsl@hotmail.com
License: MIT Licence
Keywords: karel
Platform: UNKNOWN
